{
  "filename": "samples/malicious/0078e3961d934fcf2782d77812d2ba7177e23207099333a0cd084682ca0ef3ff.asm",
  "behavior": {
    "uses_network": 0,
    "uses_fileops": 0,
    "uses_registry": 0,
    "uses_memory": 0,
    "uses_injection": 0,
    "uses_crypto": 0,
    "uses_persist": 0
  },
  "cfg": {
    "num_blocks": 782,
    "num_edges": 32,
    "branch_density": 0.0000,
    "cyclomatic_complexity": 1.0000
  },
  "apis": [
  ],
  "opcodes": [
    {"name": "PUSH", "count": 17},
    {"name": "NOP", "count": 717},
    {"name": "TEST", "count": 33},
    {"name": "MOV", "count": 4},
    {"name": "LEA", "count": 1},
    {"name": "XOR", "count": 4},
    {"name": "SUB", "count": 1},
    {"name": "POP", "count": 2},
    {"name": "RET", "count": 2},
    {"name": "CALL", "count": 1}
  ]
}
