{
  "filename": "samples/benign/07615d1ba250df0b9c8772c31ec13e14b304d62ebe6258e6ae085cd8d3bacdb4.asm",
  "behavior": {
    "uses_network": 0,
    "uses_fileops": 1,
    "uses_registry": 1,
    "uses_memory": 1,
    "uses_injection": 1,
    "uses_crypto": 1,
    "uses_persist": 1
  },
  "cfg": {
    "num_blocks": 48819,
    "num_edges": 35845,
    "branch_density": 0.0006,
    "cyclomatic_complexity": 1.0000
  },
  "apis": [
    {"name": "AL", "count": 4},
    {"name": "R12D", "count": 4},
    {"name": "R12W", "count": 2},
    {"name": "BPL", "count": 2}
  ],
  "opcodes": [
    {"name": "MOV", "count": 18492},
    {"name": "XOR", "count": 6072},
    {"name": "TEST", "count": 9511},
    {"name": "RET", "count": 3904},
    {"name": "NOP", "count": 1871},
    {"name": "SUB", "count": 705},
    {"name": "OR", "count": 219},
    {"name": "CMP", "count": 1558},
    {"name": "ADD", "count": 851},
    {"name": "POP", "count": 3767},
    {"name": "AND", "count": 96},
    {"name": "CALL", "count": 256},
    {"name": "JMP", "count": 28},
    {"name": "PUSH", "count": 1486},
    {"name": "LEA", "count": 2},
    {"name": "LEAVE", "count": 1}
  ]
}
