{
  "filename": "samples/malicious/1dddf4dc9077931adb5fb379f30a7188bc1def5fc3abd7bc3e5feb5caf79334a.asm",
  "behavior": {
    "uses_network": 0,
    "uses_fileops": 1,
    "uses_registry": 0,
    "uses_memory": 1,
    "uses_injection": 0,
    "uses_crypto": 1,
    "uses_persist": 0
  },
  "cfg": {
    "num_blocks": 6976,
    "num_edges": 5835,
    "branch_density": 0.0027,
    "cyclomatic_complexity": 1.0000
  },
  "apis": [
    {"name": "DH", "count": 1}
  ],
  "opcodes": [
    {"name": "PUSH", "count": 2344},
    {"name": "MOV", "count": 257},
    {"name": "XOR", "count": 399},
    {"name": "TEST", "count": 109},
    {"name": "CALL", "count": 12},
    {"name": "SUB", "count": 239},
    {"name": "ADD", "count": 323},
    {"name": "CMP", "count": 246},
    {"name": "POP", "count": 2033},
    {"name": "OR", "count": 183},
    {"name": "LEAVE", "count": 201},
    {"name": "RET", "count": 178},
    {"name": "AND", "count": 165},
    {"name": "JMP", "count": 19},
    {"name": "NOP", "count": 188},
    {"name": "LEA", "count": 79},
    {"name": "SYSCALL", "count": 1}
  ]
}
