{
  "filename": "samples/malicious/2c91158a135b5ac85968d8591bb5cec9870eab94509891f73abd817aac2ecb78.asm",
  "behavior": {
    "uses_network": 0,
    "uses_fileops": 1,
    "uses_registry": 1,
    "uses_memory": 1,
    "uses_injection": 1,
    "uses_crypto": 1,
    "uses_persist": 1
  },
  "cfg": {
    "num_blocks": 5158,
    "num_edges": 4581,
    "branch_density": 0.0174,
    "cyclomatic_complexity": 1.0000
  },
  "apis": [
    {"name": "DL", "count": 1},
    {"name": "BH", "count": 2},
    {"name": "CH", "count": 1}
  ],
  "opcodes": [
    {"name": "PUSH", "count": 1741},
    {"name": "MOV", "count": 221},
    {"name": "POP", "count": 1423},
    {"name": "RET", "count": 106},
    {"name": "TEST", "count": 71},
    {"name": "XOR", "count": 124},
    {"name": "JMP", "count": 90},
    {"name": "ADD", "count": 573},
    {"name": "NOP", "count": 111},
    {"name": "AND", "count": 106},
    {"name": "SUB", "count": 91},
    {"name": "OR", "count": 173},
    {"name": "LEAVE", "count": 101},
    {"name": "CALL", "count": 61},
    {"name": "CMP", "count": 112},
    {"name": "LEA", "count": 52},
    {"name": "SYSCALL", "count": 2}
  ]
}
