{
  "filename": "samples/benign/3e917376199b13523dfb4fcc445583d9df0606ad0a6a02b111d8a3ee6b71e117.asm",
  "behavior": {
    "uses_network": 0,
    "uses_fileops": 1,
    "uses_registry": 1,
    "uses_memory": 1,
    "uses_injection": 1,
    "uses_crypto": 1,
    "uses_persist": 1
  },
  "cfg": {
    "num_blocks": 16749,
    "num_edges": 5644,
    "branch_density": 0.0010,
    "cyclomatic_complexity": 1.0000
  },
  "apis": [
    {"name": "R13D", "count": 1},
    {"name": "AL", "count": 2}
  ],
  "opcodes": [
    {"name": "ADD", "count": 489},
    {"name": "POP", "count": 637},
    {"name": "PUSH", "count": 782},
    {"name": "NOP", "count": 9757},
    {"name": "MOV", "count": 2029},
    {"name": "TEST", "count": 1252},
    {"name": "RET", "count": 524},
    {"name": "XOR", "count": 924},
    {"name": "JMP", "count": 16},
    {"name": "SUB", "count": 115},
    {"name": "CMP", "count": 112},
    {"name": "LEAVE", "count": 4},
    {"name": "AND", "count": 30},
    {"name": "OR", "count": 20},
    {"name": "CALL", "count": 56},
    {"name": "LEA", "count": 2}
  ]
}
