{
  "filename": "samples/malicious/62de4b38eb84d75712aa3a6c3c6f2e0448ce9bbb6c39a14837fa5aa33e3020a8.asm",
  "behavior": {
    "uses_network": 0,
    "uses_fileops": 0,
    "uses_registry": 0,
    "uses_memory": 0,
    "uses_injection": 0,
    "uses_crypto": 1,
    "uses_persist": 0
  },
  "cfg": {
    "num_blocks": 2590,
    "num_edges": 2448,
    "branch_density": 0.0000,
    "cyclomatic_complexity": 1.0000
  },
  "apis": [
  ],
  "opcodes": [
    {"name": "PUSH", "count": 1149},
    {"name": "POP", "count": 343},
    {"name": "XOR", "count": 759},
    {"name": "OR", "count": 142},
    {"name": "MOV", "count": 190},
    {"name": "CALL", "count": 1},
    {"name": "SUB", "count": 2},
    {"name": "NOP", "count": 1},
    {"name": "RET", "count": 3}
  ]
}
