{
  "filename": "samples/benign/809bb93af12ab0735cb76578c0cf7014cc84fadfcbf2a0daad5a73a239d94441.asm",
  "behavior": {
    "uses_network": 0,
    "uses_fileops": 0,
    "uses_registry": 0,
    "uses_memory": 0,
    "uses_injection": 0,
    "uses_crypto": 0,
    "uses_persist": 0
  },
  "cfg": {
    "num_blocks": 115,
    "num_edges": 114,
    "branch_density": 0.0000,
    "cyclomatic_complexity": 1.0000
  },
  "apis": [
  ],
  "opcodes": [
    {"name": "PUSH", "count": 55},
    {"name": "ADD", "count": 38},
    {"name": "POP", "count": 17},
    {"name": "MOV", "count": 1},
    {"name": "RET", "count": 1},
    {"name": "OR", "count": 1},
    {"name": "SUB", "count": 2}
  ]
}
