{
  "filename": "samples/malicious/821fd07366bb5e34e371db4650eef64bc6f69530ec83fad50facfa8da4585ee2.asm",
  "behavior": {
    "uses_network": 0,
    "uses_fileops": 0,
    "uses_registry": 0,
    "uses_memory": 0,
    "uses_injection": 0,
    "uses_crypto": 0,
    "uses_persist": 0
  },
  "cfg": {
    "num_blocks": 333,
    "num_edges": 304,
    "branch_density": 0.0000,
    "cyclomatic_complexity": 1.0000
  },
  "apis": [
  ],
  "opcodes": [
    {"name": "PUSH", "count": 130},
    {"name": "MOV", "count": 21},
    {"name": "TEST", "count": 5},
    {"name": "CALL", "count": 3},
    {"name": "POP", "count": 97},
    {"name": "RET", "count": 13},
    {"name": "ADD", "count": 10},
    {"name": "OR", "count": 6},
    {"name": "SUB", "count": 16},
    {"name": "CMP", "count": 5},
    {"name": "LEAVE", "count": 4},
    {"name": "XOR", "count": 11},
    {"name": "AND", "count": 5},
    {"name": "LEA", "count": 2},
    {"name": "NOP", "count": 5}
  ]
}
