{
  "filename": "samples/malicious/8a375f861957b7effcda03ba43720d5bc14eeea97a33475a78b904714283d04e.asm",
  "behavior": {
    "uses_network": 0,
    "uses_fileops": 1,
    "uses_registry": 1,
    "uses_memory": 1,
    "uses_injection": 1,
    "uses_crypto": 1,
    "uses_persist": 1
  },
  "cfg": {
    "num_blocks": 10830,
    "num_edges": 9712,
    "branch_density": 0.0005,
    "cyclomatic_complexity": 1.0000
  },
  "apis": [
    {"name": "DS", "count": 3}
  ],
  "opcodes": [
    {"name": "PUSH", "count": 2224},
    {"name": "MOV", "count": 4504},
    {"name": "POP", "count": 1424},
    {"name": "RET", "count": 468},
    {"name": "XOR", "count": 611},
    {"name": "CMP", "count": 416},
    {"name": "TEST", "count": 495},
    {"name": "ADD", "count": 177},
    {"name": "LEAVE", "count": 119},
    {"name": "CALL", "count": 101},
    {"name": "NOP", "count": 41},
    {"name": "SUB", "count": 92},
    {"name": "JMP", "count": 5},
    {"name": "AND", "count": 60},
    {"name": "OR", "count": 93}
  ]
}
