{
  "filename": "samples/benign/8d042a417c37d48336b24ca108669734e259c3298072ee95032ca4ff94928b85.asm",
  "behavior": {
    "uses_network": 0,
    "uses_fileops": 0,
    "uses_registry": 0,
    "uses_memory": 0,
    "uses_injection": 0,
    "uses_crypto": 1,
    "uses_persist": 0
  },
  "cfg": {
    "num_blocks": 9368,
    "num_edges": 6754,
    "branch_density": 0.0004,
    "cyclomatic_complexity": 1.0000
  },
  "apis": [
  ],
  "opcodes": [
    {"name": "CMP", "count": 750},
    {"name": "PUSH", "count": 448},
    {"name": "MOV", "count": 4358},
    {"name": "TEST", "count": 1824},
    {"name": "XOR", "count": 723},
    {"name": "POP", "count": 653},
    {"name": "SUB", "count": 71},
    {"name": "ADD", "count": 179},
    {"name": "RET", "count": 302},
    {"name": "NOP", "count": 26},
    {"name": "CALL", "count": 6},
    {"name": "OR", "count": 20},
    {"name": "AND", "count": 4},
    {"name": "JMP", "count": 4}
  ]
}
