{
  "filename": "samples/benign/9dd0b4db6deee989440abfeddb4280a0a55137479b15af616f506ebf3bd891fb.asm",
  "behavior": {
    "uses_network": 0,
    "uses_fileops": 1,
    "uses_registry": 1,
    "uses_memory": 1,
    "uses_injection": 0,
    "uses_crypto": 1,
    "uses_persist": 1
  },
  "cfg": {
    "num_blocks": 2625,
    "num_edges": 1671,
    "branch_density": 0.0004,
    "cyclomatic_complexity": 1.0000
  },
  "apis": [
  ],
  "opcodes": [
    {"name": "RET", "count": 113},
    {"name": "XOR", "count": 194},
    {"name": "TEST", "count": 272},
    {"name": "ADD", "count": 48},
    {"name": "PUSH", "count": 188},
    {"name": "MOV", "count": 787},
    {"name": "CMP", "count": 65},
    {"name": "CALL", "count": 17},
    {"name": "POP", "count": 267},
    {"name": "NOP", "count": 617},
    {"name": "SUB", "count": 38},
    {"name": "OR", "count": 13},
    {"name": "AND", "count": 5},
    {"name": "JMP", "count": 1}
  ]
}
