{
  "filename": "samples/benign/a0899e167143ab97b167b6ae1bb270d9ba4b4e268b4a1eeb876a8b56345f23f5.asm",
  "behavior": {
    "uses_network": 0,
    "uses_fileops": 1,
    "uses_registry": 1,
    "uses_memory": 1,
    "uses_injection": 1,
    "uses_crypto": 1,
    "uses_persist": 1
  },
  "cfg": {
    "num_blocks": 27677,
    "num_edges": 23760,
    "branch_density": 0.0002,
    "cyclomatic_complexity": 1.0000
  },
  "apis": [
    {"name": "BL", "count": 2},
    {"name": "AL", "count": 59},
    {"name": "DS", "count": 1},
    {"name": "DI", "count": 4},
    {"name": "AX", "count": 4}
  ],
  "opcodes": [
    {"name": "PUSH", "count": 8926},
    {"name": "MOV", "count": 5531},
    {"name": "XOR", "count": 2194},
    {"name": "POP", "count": 4409},
    {"name": "RET", "count": 1276},
    {"name": "TEST", "count": 2944},
    {"name": "CMP", "count": 868},
    {"name": "OR", "count": 166},
    {"name": "ADD", "count": 342},
    {"name": "SUB", "count": 578},
    {"name": "NOP", "count": 21},
    {"name": "CALL", "count": 246},
    {"name": "AND", "count": 157},
    {"name": "LEAVE", "count": 13},
    {"name": "JMP", "count": 6}
  ]
}
