{
  "filename": "samples/malicious/b1e5ea303ca9aa65cc5cb98370a33e6ea83d0644ca52f6686d3473ddb42ad8a8.asm",
  "behavior": {
    "uses_network": 0,
    "uses_fileops": 1,
    "uses_registry": 1,
    "uses_memory": 1,
    "uses_injection": 1,
    "uses_crypto": 1,
    "uses_persist": 1
  },
  "cfg": {
    "num_blocks": 2019,
    "num_edges": 1655,
    "branch_density": 0.0005,
    "cyclomatic_complexity": 1.0000
  },
  "apis": [
    {"name": "BL", "count": 1},
    {"name": "AL", "count": 1},
    {"name": "DS", "count": 3}
  ],
  "opcodes": [
    {"name": "PUSH", "count": 544},
    {"name": "MOV", "count": 237},
    {"name": "TEST", "count": 171},
    {"name": "POP", "count": 384},
    {"name": "CALL", "count": 39},
    {"name": "RET", "count": 171},
    {"name": "XOR", "count": 157},
    {"name": "ADD", "count": 62},
    {"name": "SUB", "count": 20},
    {"name": "LEAVE", "count": 39},
    {"name": "JMP", "count": 1},
    {"name": "CMP", "count": 132},
    {"name": "NOP", "count": 21},
    {"name": "AND", "count": 14},
    {"name": "OR", "count": 27}
  ]
}
