{
  "filename": "samples/malicious/bcdae5b2d0961fa5e265022f7a4edfa18144d770b1b09dabd8ba5f91f8573f79.asm",
  "behavior": {
    "uses_network": 0,
    "uses_fileops": 0,
    "uses_registry": 0,
    "uses_memory": 0,
    "uses_injection": 0,
    "uses_crypto": 1,
    "uses_persist": 0
  },
  "cfg": {
    "num_blocks": 331,
    "num_edges": 298,
    "branch_density": 0.0000,
    "cyclomatic_complexity": 1.0000
  },
  "apis": [
  ],
  "opcodes": [
    {"name": "MOV", "count": 38},
    {"name": "PUSH", "count": 116},
    {"name": "POP", "count": 93},
    {"name": "XOR", "count": 36},
    {"name": "NOP", "count": 28},
    {"name": "CALL", "count": 2},
    {"name": "SUB", "count": 4},
    {"name": "TEST", "count": 2},
    {"name": "AND", "count": 1},
    {"name": "ADD", "count": 4},
    {"name": "RET", "count": 3},
    {"name": "OR", "count": 1},
    {"name": "CMP", "count": 1},
    {"name": "LEA", "count": 1},
    {"name": "LEAVE", "count": 1}
  ]
}
