{
  "filename": "cnetnet/CNET_103189.asm",
  "behavior": {
    "uses_network": 0,
    "uses_fileops": 0,
    "uses_registry": 0,
    "uses_memory": 0,
    "uses_injection": 0,
    "uses_crypto": 0,
    "uses_persist": 0
  },
  "cfg": {
    "num_blocks": 250,
    "num_edges": 247,
    "branch_density": 0.0000,
    "cyclomatic_complexity": 1.0000
  },
  "apis": [
    {"name": "BYTE", "count": 1173},
    {"name": "AL", "count": 150},
    {"name": "EAX", "count": 219},
    {"name": "ESI", "count": 45},
    {"name": "DWORD", "count": 514},
    {"name": "ES", "count": 40},
    {"name": "SS", "count": 23},
    {"name": "CH", "count": 29},
    {"name": "ECX", "count": 63},
    {"name": "EBP", "count": 76},
    {"name": "INC", "count": 56},
    {"name": "DX", "count": 172},
    {"name": "DL", "count": 27},
    {"name": "BH", "count": 14},
    {"name": "WORD", "count": 65},
    {"name": "DS", "count": 16},
    {"name": "DH", "count": 16},
    {"name": "BL", "count": 16},
    {"name": "AH", "count": 14},
    {"name": "BAD", "count": 7},
    {"name": "EBX", "count": 51},
    {"name": "CLC", "count": 1},
    {"name": "CL", "count": 17},
    {"name": "EDX", "count": 21},
    {"name": "EDI", "count": 23},
    {"name": "SBB", "count": 2},
    {"name": "XMMWORD", "count": 1},
    {"name": "ESP", "count": 62},
    {"name": "DEC", "count": 48},
    {"name": "FWORD", "count": 3},
    {"name": "DAA", "count": 5},
    {"name": "AAA", "count": 1},
    {"name": "QWORD", "count": 43},
    {"name": "LAHF", "count": 2},
    {"name": "INT3", "count": 1},
    {"name": "POPA", "count": 85},
    {"name": "INT1", "count": 1},
    {"name": "XCHG", "count": 7},
    {"name": "DAS", "count": 1},
    {"name": "AX", "count": 4},
    {"name": "STC", "count": 2},
    {"name": "INS", "count": 30},
    {"name": "GS", "count": 12},
    {"name": "CS", "count": 16},
    {"name": "DATA16", "count": 1},
    {"name": "SP", "count": 1},
    {"name": "ADDR16", "count": 1},
    {"name": "JO", "count": 4},
    {"name": "OUTS", "count": 2},
    {"name": "PUSHA", "count": 1},
    {"name": "JS", "count": 1},
    {"name": "JNO", "count": 1},
    {"name": "AAS", "count": 1},
    {"name": "PUSHF", "count": 1},
    {"name": "CDQ", "count": 1}
  ],
  "opcodes": [
    {"name": "PUSH", "count": 141},
    {"name": "POP", "count": 57},
    {"name": "ADD", "count": 44},
    {"name": "CALL", "count": 2},
    {"name": "AND", "count": 1},
    {"name": "CMP", "count": 1},
    {"name": "RET", "count": 1},
    {"name": "LEA", "count": 2},
    {"name": "LEAVE", "count": 1}
  ]
}
