{
  "filename": "cnetnet/CNET_102802.asm",
  "behavior": {
    "uses_network": 0,
    "uses_fileops": 0,
    "uses_registry": 0,
    "uses_memory": 0,
    "uses_injection": 0,
    "uses_crypto": 0,
    "uses_persist": 0
  },
  "cfg": {
    "num_blocks": 1574,
    "num_edges": 1498,
    "branch_density": 0.0000,
    "cyclomatic_complexity": 1.0000
  },
  "apis": [
    {"name": "EBP", "count": 366},
    {"name": "DWORD", "count": 2214},
    {"name": "BYTE", "count": 5785},
    {"name": "AL", "count": 1222},
    {"name": "EAX", "count": 947},
    {"name": "SS", "count": 144},
    {"name": "CH", "count": 213},
    {"name": "DX", "count": 750},
    {"name": "WORD", "count": 276},
    {"name": "ES", "count": 458},
    {"name": "INC", "count": 355},
    {"name": "ESI", "count": 250},
    {"name": "BH", "count": 207},
    {"name": "BL", "count": 104},
    {"name": "DH", "count": 107},
    {"name": "CL", "count": 167},
    {"name": "DS", "count": 76},
    {"name": "DL", "count": 168},
    {"name": "ECX", "count": 268},
    {"name": "BAD", "count": 45},
    {"name": "QWORD", "count": 118},
    {"name": "DAA", "count": 20},
    {"name": "EDX", "count": 165},
    {"name": "EBX", "count": 260},
    {"name": "DAS", "count": 21},
    {"name": "DEC", "count": 251},
    {"name": "AAA", "count": 19},
    {"name": "EDI", "count": 178},
    {"name": "ESP", "count": 243},
    {"name": "AH", "count": 106},
    {"name": "CS", "count": 124},
    {"name": "PUSHA", "count": 14},
    {"name": "CDQ", "count": 7},
    {"name": "POPF", "count": 5},
    {"name": "ADC", "count": 12},
    {"name": "POPA", "count": 312},
    {"name": "XCHG", "count": 66},
    {"name": "CWDE", "count": 4},
    {"name": "PUSHF", "count": 6},
    {"name": "LAHF", "count": 10},
    {"name": "FWAIT", "count": 5},
    {"name": "PUSHW", "count": 1},
    {"name": "FWORD", "count": 9},
    {"name": "GS", "count": 93},
    {"name": "IN", "count": 7},
    {"name": "OUT", "count": 7},
    {"name": "HLT", "count": 8},
    {"name": "CMC", "count": 6},
    {"name": "STC", "count": 4},
    {"name": "INT1", "count": 13},
    {"name": "CLI", "count": 6},
    {"name": "AAS", "count": 9},
    {"name": "IRET", "count": 4},
    {"name": "INT3", "count": 6},
    {"name": "SBB", "count": 11},
    {"name": "CLD", "count": 5},
    {"name": "INTO", "count": 2},
    {"name": "STD", "count": 12},
    {"name": "SAHF", "count": 2},
    {"name": "CLC", "count": 1},
    {"name": "SYSENTER", "count": 1},
    {"name": "XMM0", "count": 1},
    {"name": "RETF", "count": 1},
    {"name": "SYSRET", "count": 1},
    {"name": "SP", "count": 3},
    {"name": "INS", "count": 38},
    {"name": "FS", "count": 17},
    {"name": "DATA16", "count": 5},
    {"name": "JNS", "count": 3},
    {"name": "BX", "count": 2},
    {"name": "JNO", "count": 5},
    {"name": "OUTS", "count": 6},
    {"name": "JS", "count": 10},
    {"name": "ADDR16", "count": 3},
    {"name": "JO", "count": 16},
    {"name": "DI", "count": 4},
    {"name": "IMUL", "count": 3},
    {"name": "BP", "count": 1},
    {"name": "POPAW", "count": 2},
    {"name": "MM0", "count": 1},
    {"name": "CR1", "count": 1},
    {"name": "MM3", "count": 1},
    {"name": "ST", "count": 1},
    {"name": "BOUND", "count": 1}
  ],
  "opcodes": [
    {"name": "PUSH", "count": 888},
    {"name": "POP", "count": 331},
    {"name": "OR", "count": 40},
    {"name": "TEST", "count": 2},
    {"name": "NOP", "count": 8},
    {"name": "LEA", "count": 16},
    {"name": "ADD", "count": 231},
    {"name": "AND", "count": 4},
    {"name": "RET", "count": 8},
    {"name": "SUB", "count": 36},
    {"name": "LEAVE", "count": 5},
    {"name": "CALL", "count": 1},
    {"name": "CMP", "count": 2},
    {"name": "MOV", "count": 1},
    {"name": "XOR", "count": 1}
  ]
}
