{
  "filename": "samples/benign/d3062f93740551d2f3aa0a386587f7cc5ab4c524477845ca4d2544764d0bf119.asm",
  "behavior": {
    "uses_network": 0,
    "uses_fileops": 0,
    "uses_registry": 0,
    "uses_memory": 0,
    "uses_injection": 0,
    "uses_crypto": 0,
    "uses_persist": 0
  },
  "cfg": {
    "num_blocks": 415,
    "num_edges": 313,
    "branch_density": 0.0000,
    "cyclomatic_complexity": 1.0000
  },
  "apis": [
  ],
  "opcodes": [
    {"name": "PUSH", "count": 166},
    {"name": "ADD", "count": 62},
    {"name": "LEA", "count": 35},
    {"name": "POP", "count": 68},
    {"name": "OR", "count": 68},
    {"name": "CALL", "count": 7},
    {"name": "CMP", "count": 3},
    {"name": "NOP", "count": 1},
    {"name": "SUB", "count": 1},
    {"name": "AND", "count": 2},
    {"name": "RET", "count": 2}
  ]
}
