{
  "filename": "samples/malicious/dc0a3ba629352a9d1a01825eb50406021b4ab938ba5a9bb7f56c4f03b3697637.asm",
  "behavior": {
    "uses_network": 0,
    "uses_fileops": 1,
    "uses_registry": 1,
    "uses_memory": 1,
    "uses_injection": 1,
    "uses_crypto": 1,
    "uses_persist": 1
  },
  "cfg": {
    "num_blocks": 5805,
    "num_edges": 4755,
    "branch_density": 0.0022,
    "cyclomatic_complexity": 1.0000
  },
  "apis": [
    {"name": "DS", "count": 3}
  ],
  "opcodes": [
    {"name": "AND", "count": 132},
    {"name": "PUSH", "count": 1808},
    {"name": "XOR", "count": 282},
    {"name": "RET", "count": 279},
    {"name": "LEAVE", "count": 152},
    {"name": "CALL", "count": 42},
    {"name": "POP", "count": 1594},
    {"name": "LEA", "count": 50},
    {"name": "NOP", "count": 179},
    {"name": "ADD", "count": 166},
    {"name": "CMP", "count": 237},
    {"name": "OR", "count": 128},
    {"name": "MOV", "count": 382},
    {"name": "SUB", "count": 134},
    {"name": "TEST", "count": 226},
    {"name": "JMP", "count": 13},
    {"name": "SYSCALL", "count": 1}
  ]
}
