{
  "filename": "samples/malicious/e22a77db2308908a70b8a10aa6b582d42cb361244b178f0a6c3c51999a5dfd53.asm",
  "behavior": {
    "uses_network": 0,
    "uses_fileops": 0,
    "uses_registry": 0,
    "uses_memory": 0,
    "uses_injection": 0,
    "uses_crypto": 1,
    "uses_persist": 0
  },
  "cfg": {
    "num_blocks": 5875,
    "num_edges": 4922,
    "branch_density": 0.0034,
    "cyclomatic_complexity": 1.0000
  },
  "apis": [
  ],
  "opcodes": [
    {"name": "PUSH", "count": 1861},
    {"name": "MOV", "count": 390},
    {"name": "CMP", "count": 187},
    {"name": "XOR", "count": 335},
    {"name": "ADD", "count": 386},
    {"name": "POP", "count": 1574},
    {"name": "NOP", "count": 148},
    {"name": "AND", "count": 132},
    {"name": "OR", "count": 157},
    {"name": "TEST", "count": 97},
    {"name": "SUB", "count": 175},
    {"name": "LEAVE", "count": 171},
    {"name": "RET", "count": 143},
    {"name": "LEA", "count": 90},
    {"name": "JMP", "count": 20},
    {"name": "CALL", "count": 9}
  ]
}
