{
  "filename": "samples/benign/e68d0aff6f9b17d0c48a18f79e0f405f420242ac9c0c4579c8cced7ef699aa46.asm",
  "behavior": {
    "uses_network": 0,
    "uses_fileops": 1,
    "uses_registry": 1,
    "uses_memory": 1,
    "uses_injection": 1,
    "uses_crypto": 1,
    "uses_persist": 1
  },
  "cfg": {
    "num_blocks": 4244,
    "num_edges": 3163,
    "branch_density": 0.0002,
    "cyclomatic_complexity": 1.0000
  },
  "apis": [
    {"name": "R13D", "count": 2}
  ],
  "opcodes": [
    {"name": "RET", "count": 196},
    {"name": "XOR", "count": 513},
    {"name": "MOV", "count": 1584},
    {"name": "TEST", "count": 1015},
    {"name": "SUB", "count": 92},
    {"name": "ADD", "count": 55},
    {"name": "POP", "count": 340},
    {"name": "PUSH", "count": 317},
    {"name": "CALL", "count": 32},
    {"name": "CMP", "count": 81},
    {"name": "AND", "count": 5},
    {"name": "OR", "count": 7},
    {"name": "NOP", "count": 6},
    {"name": "JMP", "count": 1}
  ]
}
