{
  "filename": "samples/benign/ebb96f004f982d3aa4d5e92342637148d66d7133e6b8096e72e8f34560c73aa5.asm",
  "behavior": {
    "uses_network": 0,
    "uses_fileops": 0,
    "uses_registry": 0,
    "uses_memory": 0,
    "uses_injection": 0,
    "uses_crypto": 1,
    "uses_persist": 0
  },
  "cfg": {
    "num_blocks": 2226,
    "num_edges": 1278,
    "branch_density": 0.0004,
    "cyclomatic_complexity": 1.0000
  },
  "apis": [
  ],
  "opcodes": [
    {"name": "PUSH", "count": 261},
    {"name": "MOV", "count": 367},
    {"name": "TEST", "count": 357},
    {"name": "LEAVE", "count": 22},
    {"name": "RET", "count": 127},
    {"name": "POP", "count": 282},
    {"name": "NOP", "count": 487},
    {"name": "XOR", "count": 174},
    {"name": "ADD", "count": 28},
    {"name": "AND", "count": 15},
    {"name": "CMP", "count": 56},
    {"name": "SUB", "count": 29},
    {"name": "OR", "count": 16},
    {"name": "CALL", "count": 4},
    {"name": "JMP", "count": 1}
  ]
}
