{
  "filename": "samples/malicious/ee177b068a2ac964536637fe4f04ff2deed524e981e69f5cceb2e0dd935c3f65.asm",
  "behavior": {
    "uses_network": 0,
    "uses_fileops": 1,
    "uses_registry": 1,
    "uses_memory": 1,
    "uses_injection": 1,
    "uses_crypto": 1,
    "uses_persist": 1
  },
  "cfg": {
    "num_blocks": 12412,
    "num_edges": 10613,
    "branch_density": 0.0053,
    "cyclomatic_complexity": 1.0000
  },
  "apis": [
    {"name": "DS", "count": 1}
  ],
  "opcodes": [
    {"name": "RET", "count": 352},
    {"name": "LEAVE", "count": 364},
    {"name": "PUSH", "count": 4367},
    {"name": "ADD", "count": 382},
    {"name": "AND", "count": 319},
    {"name": "POP", "count": 4291},
    {"name": "NOP", "count": 327},
    {"name": "XOR", "count": 312},
    {"name": "OR", "count": 319},
    {"name": "SUB", "count": 274},
    {"name": "CMP", "count": 316},
    {"name": "MOV", "count": 415},
    {"name": "TEST", "count": 140},
    {"name": "JMP", "count": 66},
    {"name": "LEA", "count": 120},
    {"name": "CALL", "count": 44},
    {"name": "SYSCALL", "count": 4}
  ]
}
