{
  "filename": "samples/benign/efecf9bb87d641994cab084a0ad65397b193c7a6d00c65100e6e41b8948f592e.asm",
  "behavior": {
    "uses_network": 0,
    "uses_fileops": 0,
    "uses_registry": 0,
    "uses_memory": 0,
    "uses_injection": 0,
    "uses_crypto": 1,
    "uses_persist": 0
  },
  "cfg": {
    "num_blocks": 1626,
    "num_edges": 824,
    "branch_density": 0.0006,
    "cyclomatic_complexity": 1.0000
  },
  "apis": [
  ],
  "opcodes": [
    {"name": "PUSH", "count": 154},
    {"name": "MOV", "count": 242},
    {"name": "TEST", "count": 256},
    {"name": "LEAVE", "count": 17},
    {"name": "RET", "count": 88},
    {"name": "XOR", "count": 102},
    {"name": "NOP", "count": 479},
    {"name": "CMP", "count": 27},
    {"name": "AND", "count": 7},
    {"name": "SUB", "count": 21},
    {"name": "ADD", "count": 22},
    {"name": "POP", "count": 189},
    {"name": "OR", "count": 19},
    {"name": "CALL", "count": 2},
    {"name": "JMP", "count": 1}
  ]
}
