{
  "filename": "samples/benign/f7df2fc6c007aa22af62210420d1f16df04f3cfd9ada02d29952af3d3783556e.asm",
  "behavior": {
    "uses_network": 0,
    "uses_fileops": 1,
    "uses_registry": 0,
    "uses_memory": 1,
    "uses_injection": 0,
    "uses_crypto": 1,
    "uses_persist": 0
  },
  "cfg": {
    "num_blocks": 3136,
    "num_edges": 2726,
    "branch_density": 0.0013,
    "cyclomatic_complexity": 1.0000
  },
  "apis": [
  ],
  "opcodes": [
    {"name": "ADD", "count": 75},
    {"name": "POP", "count": 471},
    {"name": "PUSH", "count": 1083},
    {"name": "MOV", "count": 637},
    {"name": "CMP", "count": 57},
    {"name": "NOP", "count": 2},
    {"name": "RET", "count": 103},
    {"name": "XOR", "count": 287},
    {"name": "TEST", "count": 361},
    {"name": "AND", "count": 5},
    {"name": "OR", "count": 4},
    {"name": "SUB", "count": 32},
    {"name": "CALL", "count": 15},
    {"name": "JMP", "count": 4}
  ]
}
