{
  "filename": "SysinternalsSuite/FindLinks.asm",
  "behavior": {
    "uses_network": 0,
    "uses_fileops": 0,
    "uses_registry": 0,
    "uses_memory": 0,
    "uses_injection": 0,
    "uses_crypto": 0,
    "uses_persist": 0
  },
  "cfg": {
    "num_blocks": 11011,
    "num_edges": 9358,
    "branch_density": 0.0005,
    "cyclomatic_complexity": 1.0000
  },
  "apis": [
    {"name": "EBP", "count": 2255},
    {"name": "ESP", "count": 1332},
    {"name": "EAX", "count": 7226},
    {"name": "DWORD", "count": 6633},
    {"name": "EDI", "count": 2849},
    {"name": "ECX", "count": 3733},
    {"name": "ESI", "count": 3061},
    {"name": "INT3", "count": 564},
    {"name": "EBX", "count": 1431},
    {"name": "EDX", "count": 1304},
    {"name": "INC", "count": 293},
    {"name": "AL", "count": 792},
    {"name": "SETE", "count": 33},
    {"name": "CMOVS", "count": 2},
    {"name": "WORD", "count": 420},
    {"name": "NEG", "count": 57},
    {"name": "SBB", "count": 63},
    {"name": "XMM0", "count": 110},
    {"name": "XORPS", "count": 2},
    {"name": "QWORD", "count": 167},
    {"name": "XMMWORD", "count": 173},
    {"name": "CDQ", "count": 14},
    {"name": "IDIV", "count": 3},
    {"name": "CL", "count": 248},
    {"name": "BYTE", "count": 725},
    {"name": "CMOVG", "count": 1},
    {"name": "AX", "count": 329},
    {"name": "SAR", "count": 23},
    {"name": "CX", "count": 51},
    {"name": "CMOVE", "count": 15},
    {"name": "BL", "count": 133},
    {"name": "MOVSX", "count": 15},
    {"name": "SETNE", "count": 24},
    {"name": "CMOVNE", "count": 4},
    {"name": "DEC", "count": 107},
    {"name": "DX", "count": 60},
    {"name": "XCHG", "count": 4},
    {"name": "MUL", "count": 10},
    {"name": "CMOVBE", "count": 2},
    {"name": "MOVZX", "count": 100},
    {"name": "PUSHF", "count": 3},
    {"name": "FNCLEX", "count": 3},
    {"name": "ROR", "count": 30},
    {"name": "CMPXCHG", "count": 1},
    {"name": "NOT", "count": 30},
    {"name": "CPUID", "count": 3},
    {"name": "XGETBV", "count": 1},
    {"name": "CLD", "count": 6},
    {"name": "SI", "count": 145},
    {"name": "MOVD", "count": 12},
    {"name": "XMM2", "count": 51},
    {"name": "XMM1", "count": 83},
    {"name": "PXOR", "count": 7},
    {"name": "PCMPEQW", "count": 3},
    {"name": "POR", "count": 2},
    {"name": "PMOVMSKB", "count": 9},
    {"name": "BSF", "count": 3},
    {"name": "MOVS", "count": 8},
    {"name": "DL", "count": 84},
    {"name": "STOS", "count": 4},
    {"name": "XMM3", "count": 47},
    {"name": "XMM5", "count": 29},
    {"name": "MOVDQA", "count": 18},
    {"name": "XMM4", "count": 25},
    {"name": "PUSHA", "count": 4},
    {"name": "STD", "count": 3},
    {"name": "CH", "count": 31},
    {"name": "AH", "count": 54},
    {"name": "BH", "count": 10},
    {"name": "XMM6", "count": 20},
    {"name": "XMM7", "count": 13},
    {"name": "SHR", "count": 27},
    {"name": "DIV", "count": 16},
    {"name": "BX", "count": 19},
    {"name": "DH", "count": 5},
    {"name": "DI", "count": 19},
    {"name": "CBW", "count": 2},
    {"name": "XADD", "count": 7},
    {"name": "IMUL", "count": 3},
    {"name": "YMM1", "count": 8},
    {"name": "VXORPS", "count": 2},
    {"name": "YMM0", "count": 4},
    {"name": "YMMWORD", "count": 2},
    {"name": "VPMOVMSKB", "count": 2},
    {"name": "VZEROUPPER", "count": 2},
    {"name": "PCMPEQB", "count": 5},
    {"name": "SETG", "count": 3},
    {"name": "SETL", "count": 1},
    {"name": "ADC", "count": 11},
    {"name": "BSR", "count": 7},
    {"name": "SHL", "count": 17},
    {"name": "SETA", "count": 5},
    {"name": "SETB", "count": 3},
    {"name": "TBYTE", "count": 23},
    {"name": "FWAIT", "count": 9},
    {"name": "FSTSW", "count": 8},
    {"name": "FLDZ", "count": 17},
    {"name": "FLD1", "count": 10},
    {"name": "ST", "count": 99},
    {"name": "FLDPI", "count": 1},
    {"name": "FLDLG2", "count": 2},
    {"name": "FYL2X", "count": 4},
    {"name": "MOVAPD", "count": 8},
    {"name": "PSUBD", "count": 1},
    {"name": "PSRLQ", "count": 1},
    {"name": "PSLLQ", "count": 2},
    {"name": "UCOMISD", "count": 1},
    {"name": "CMPNLEPD", "count": 1},
    {"name": "ADDSD", "count": 5},
    {"name": "SETNS", "count": 1},
    {"name": "UNPCKLPD", "count": 2},
    {"name": "ANDPD", "count": 4},
    {"name": "ORPD", "count": 2},
    {"name": "ADDPD", "count": 7},
    {"name": "SUBPD", "count": 2},
    {"name": "MULPD", "count": 8},
    {"name": "CVTSI2SD", "count": 1},
    {"name": "MULSD", "count": 3},
    {"name": "UNPCKHPD", "count": 2},
    {"name": "CMPEQSD", "count": 2},
    {"name": "DIVSD", "count": 2},
    {"name": "XORPD", "count": 1},
    {"name": "FLDL2E", "count": 1},
    {"name": "FSCALE", "count": 4},
    {"name": "FCHS", "count": 11},
    {"name": "FABS", "count": 6},
    {"name": "FLDLN2", "count": 2},
    {"name": "FTST", "count": 4},
    {"name": "FCOMPP", "count": 4},
    {"name": "FRNDINT", "count": 5},
    {"name": "F2XM1", "count": 2},
    {"name": "SAHF", "count": 4},
    {"name": "FXAM", "count": 3},
    {"name": "ROL", "count": 3},
    {"name": "FNSTSW", "count": 20},
    {"name": "FUCOMPP", "count": 3},
    {"name": "RCR", "count": 6},
    {"name": "SHRD", "count": 1},
    {"name": "SHLD", "count": 1},
    {"name": "MOVLHPS", "count": 2},
    {"name": "CMOVB", "count": 1},
    {"name": "SCAS", "count": 2}
  ],
  "opcodes": [
    {"name": "PUSH", "count": 2914},
    {"name": "MOV", "count": 2138},
    {"name": "XOR", "count": 851},
    {"name": "TEST", "count": 1024},
    {"name": "POP", "count": 2180},
    {"name": "RET", "count": 776},
    {"name": "CMP", "count": 481},
    {"name": "CALL", "count": 83},
    {"name": "NOP", "count": 21},
    {"name": "SUB", "count": 171},
    {"name": "ADD", "count": 152},
    {"name": "LEAVE", "count": 34},
    {"name": "OR", "count": 90},
    {"name": "JMP", "count": 5},
    {"name": "AND", "count": 91}
  ]
}
