{
  "filename": "SysinternalsSuite/LoadOrd64.asm",
  "behavior": {
    "uses_network": 0,
    "uses_fileops": 0,
    "uses_registry": 0,
    "uses_memory": 0,
    "uses_injection": 0,
    "uses_crypto": 0,
    "uses_persist": 0
  },
  "cfg": {
    "num_blocks": 24158,
    "num_edges": 18775,
    "branch_density": 0.0004,
    "cyclomatic_complexity": 1.0000
  },
  "apis": [
    {"name": "RBX", "count": 4127},
    {"name": "RSI", "count": 1739},
    {"name": "RDI", "count": 2900},
    {"name": "R12", "count": 483},
    {"name": "R14", "count": 1232},
    {"name": "R15", "count": 732},
    {"name": "RBP", "count": 2302},
    {"name": "RSP", "count": 4630},
    {"name": "RAX", "count": 8315},
    {"name": "QWORD", "count": 14246},
    {"name": "RCX", "count": 7800},
    {"name": "ESI", "count": 771},
    {"name": "R9D", "count": 1364},
    {"name": "ECX", "count": 4234},
    {"name": "DWORD", "count": 7834},
    {"name": "R10D", "count": 407},
    {"name": "R8D", "count": 2259},
    {"name": "RDX", "count": 4609},
    {"name": "EBX", "count": 1414},
    {"name": "RIP", "count": 1285},
    {"name": "R8", "count": 2511},
    {"name": "EAX", "count": 7864},
    {"name": "BYTE", "count": 2731},
    {"name": "AL", "count": 3502},
    {"name": "R9", "count": 1463},
    {"name": "CMOVNE", "count": 73},
    {"name": "XMM0", "count": 513},
    {"name": "XORPS", "count": 50},
    {"name": "XMMWORD", "count": 699},
    {"name": "EDX", "count": 3261},
    {"name": "MOVSXD", "count": 235},
    {"name": "INT3", "count": 5261},
    {"name": "R11", "count": 502},
    {"name": "CDQ", "count": 10},
    {"name": "SAR", "count": 64},
    {"name": "R14D", "count": 468},
    {"name": "R15D", "count": 342},
    {"name": "AX", "count": 670},
    {"name": "XCHG", "count": 15},
    {"name": "INC", "count": 651},
    {"name": "WORD", "count": 1166},
    {"name": "R13", "count": 375},
    {"name": "EDI", "count": 999},
    {"name": "CMOVB", "count": 28},
    {"name": "R12D", "count": 292},
    {"name": "EBP", "count": 343},
    {"name": "R13D", "count": 171},
    {"name": "DATA16", "count": 12},
    {"name": "CL", "count": 718},
    {"name": "MOVSX", "count": 66},
    {"name": "CMOVS", "count": 23},
    {"name": "R15B", "count": 195},
    {"name": "SETE", "count": 148},
    {"name": "R8W", "count": 64},
    {"name": "MOVZX", "count": 274},
    {"name": "R11D", "count": 318},
    {"name": "R10", "count": 493},
    {"name": "CMOVE", "count": 159},
    {"name": "IDIV", "count": 4},
    {"name": "SIL", "count": 145},
    {"name": "SETNE", "count": 135},
    {"name": "DEC", "count": 127},
    {"name": "DIL", "count": 98},
    {"name": "BL", "count": 205},
    {"name": "CMOVG", "count": 8},
    {"name": "DX", "count": 191},
    {"name": "NEG", "count": 178},
    {"name": "R10W", "count": 14},
    {"name": "CX", "count": 284},
    {"name": "CMPXCHG", "count": 7},
    {"name": "DL", "count": 477},
    {"name": "SBB", "count": 116},
    {"name": "NOT", "count": 99},
    {"name": "SETBE", "count": 16},
    {"name": "SETA", "count": 13},
    {"name": "CPUID", "count": 4},
    {"name": "BT", "count": 55},
    {"name": "XGETBV", "count": 2},
    {"name": "R11B", "count": 25},
    {"name": "SHL", "count": 30},
    {"name": "MOVD", "count": 16},
    {"name": "XMM1", "count": 284},
    {"name": "XMM2", "count": 105},
    {"name": "MOVDQA", "count": 15},
    {"name": "POR", "count": 4},
    {"name": "PMOVMSKB", "count": 22},
    {"name": "BSF", "count": 5},
    {"name": "BSR", "count": 7},
    {"name": "R8B", "count": 281},
    {"name": "STOS", "count": 12},
    {"name": "IMUL", "count": 59},
    {"name": "MOVQ", "count": 14},
    {"name": "PUNPCKLBW", "count": 3},
    {"name": "SFENCE", "count": 2},
    {"name": "MOVS", "count": 1},
    {"name": "YMM0", "count": 18},
    {"name": "YMMWORD", "count": 80},
    {"name": "YMM5", "count": 1},
    {"name": "YMM1", "count": 36},
    {"name": "YMM2", "count": 4},
    {"name": "YMM3", "count": 4},
    {"name": "YMM4", "count": 4},
    {"name": "VZEROUPPER", "count": 13},
    {"name": "XMM5", "count": 41},
    {"name": "XMM3", "count": 54},
    {"name": "XMM4", "count": 43},
    {"name": "MOVUPS", "count": 1},
    {"name": "MOVAPS", "count": 14},
    {"name": "CMOVBE", "count": 9},
    {"name": "CMOVA", "count": 42},
    {"name": "CQO", "count": 4},
    {"name": "MUL", "count": 10},
    {"name": "R10B", "count": 54},
    {"name": "R9B", "count": 172},
    {"name": "SHR", "count": 208},
    {"name": "BPL", "count": 85},
    {"name": "R14B", "count": 66},
    {"name": "CMOVGE", "count": 2},
    {"name": "CVTPS2PD", "count": 4},
    {"name": "R12B", "count": 15},
    {"name": "R13B", "count": 21},
    {"name": "SETLE", "count": 1},
    {"name": "XMM6", "count": 57},
    {"name": "SETB", "count": 17},
    {"name": "SETAE", "count": 3},
    {"name": "DIV", "count": 39},
    {"name": "R14W", "count": 13},
    {"name": "R9W", "count": 42},
    {"name": "DI", "count": 18},
    {"name": "BP", "count": 32},
    {"name": "R12W", "count": 15},
    {"name": "SI", "count": 34},
    {"name": "FWAIT", "count": 1},
    {"name": "R15W", "count": 7},
    {"name": "CMOVLE", "count": 12},
    {"name": "CMOVL", "count": 2},
    {"name": "ROR", "count": 58},
    {"name": "CDQE", "count": 14},
    {"name": "XADD", "count": 20},
    {"name": "BX", "count": 195},
    {"name": "R11W", "count": 14},
    {"name": "VPXOR", "count": 11},
    {"name": "VPMOVMSKB", "count": 10},
    {"name": "PCMPEQW", "count": 5},
    {"name": "PCMPEQB", "count": 4},
    {"name": "CMOVNS", "count": 5},
    {"name": "SETG", "count": 1},
    {"name": "SETGE", "count": 2},
    {"name": "CVTTSD2SI", "count": 2},
    {"name": "CMOVAE", "count": 15},
    {"name": "BTS", "count": 1},
    {"name": "BH", "count": 1},
    {"name": "RCR", "count": 1},
    {"name": "ST", "count": 4},
    {"name": "STD", "count": 1},
    {"name": "BAD", "count": 7},
    {"name": "OUT", "count": 1},
    {"name": "CLI", "count": 1},
    {"name": "AH", "count": 1},
    {"name": "ADC", "count": 1},
    {"name": "PUSHF", "count": 1},
    {"name": "ESP", "count": 1},
    {"name": "MOVAPD", "count": 13},
    {"name": "CVTDQ2PD", "count": 2},
    {"name": "XORPD", "count": 1},
    {"name": "COMISD", "count": 3},
    {"name": "SUBSD", "count": 4},
    {"name": "MULSD", "count": 23},
    {"name": "ADDSD", "count": 13},
    {"name": "DIVSD", "count": 1},
    {"name": "MOVSD", "count": 2},
    {"name": "VMOVQ", "count": 2},
    {"name": "VCVTDQ2PD", "count": 2},
    {"name": "VCOMISD", "count": 1},
    {"name": "VPADDQ", "count": 1},
    {"name": "VSUBSD", "count": 3},
    {"name": "VMULSD", "count": 9},
    {"name": "VFMADD231SD", "count": 2},
    {"name": "VFMSUB213SD", "count": 1},
    {"name": "VADDSD", "count": 9},
    {"name": "VDIVSD", "count": 1},
    {"name": "VMOVAPD", "count": 1},
    {"name": "CVTSD2SS", "count": 1},
    {"name": "CVTSD2SI", "count": 1},
    {"name": "CVTSI2SD", "count": 1},
    {"name": "XMM7", "count": 3},
    {"name": "UCOMISD", "count": 2},
    {"name": "R13W", "count": 1},
    {"name": "BSWAP", "count": 2}
  ],
  "opcodes": [
    {"name": "PUSH", "count": 1381},
    {"name": "XOR", "count": 2704},
    {"name": "MOV", "count": 8625},
    {"name": "TEST", "count": 3518},
    {"name": "SUB", "count": 588},
    {"name": "POP", "count": 1928},
    {"name": "RET", "count": 2951},
    {"name": "CMP", "count": 1295},
    {"name": "NOP", "count": 121},
    {"name": "ADD", "count": 560},
    {"name": "CALL", "count": 9},
    {"name": "AND", "count": 255},
    {"name": "OR", "count": 213},
    {"name": "JMP", "count": 10}
  ]
}
