{
  "filename": "SysinternalsSuite/PsExec64.asm",
  "behavior": {
    "uses_network": 0,
    "uses_fileops": 0,
    "uses_registry": 0,
    "uses_memory": 0,
    "uses_injection": 0,
    "uses_crypto": 0,
    "uses_persist": 0
  },
  "cfg": {
    "num_blocks": 20849,
    "num_edges": 15799,
    "branch_density": 0.0013,
    "cyclomatic_complexity": 1.0000
  },
  "apis": [
    {"name": "RSP", "count": 3195},
    {"name": "R8D", "count": 1742},
    {"name": "RDX", "count": 4478},
    {"name": "RIP", "count": 1116},
    {"name": "RCX", "count": 6949},
    {"name": "INT3", "count": 3940},
    {"name": "QWORD", "count": 11898},
    {"name": "R14", "count": 1399},
    {"name": "RSI", "count": 1940},
    {"name": "RBX", "count": 3228},
    {"name": "R8", "count": 2500},
    {"name": "RBP", "count": 2229},
    {"name": "EAX", "count": 6532},
    {"name": "WORD", "count": 1348},
    {"name": "RAX", "count": 7251},
    {"name": "ECX", "count": 3624},
    {"name": "CMOVB", "count": 57},
    {"name": "RDI", "count": 2853},
    {"name": "XMM0", "count": 917},
    {"name": "XORPS", "count": 126},
    {"name": "XMMWORD", "count": 1107},
    {"name": "EDX", "count": 2664},
    {"name": "SAR", "count": 59},
    {"name": "DL", "count": 266},
    {"name": "EBX", "count": 1130},
    {"name": "BL", "count": 129},
    {"name": "EBP", "count": 475},
    {"name": "DWORD", "count": 5062},
    {"name": "R14D", "count": 519},
    {"name": "ESI", "count": 790},
    {"name": "INC", "count": 689},
    {"name": "CMOVE", "count": 128},
    {"name": "CMOVNE", "count": 85},
    {"name": "R9D", "count": 1394},
    {"name": "EDI", "count": 942},
    {"name": "R9", "count": 1549},
    {"name": "R8W", "count": 80},
    {"name": "MOVZX", "count": 412},
    {"name": "AX", "count": 566},
    {"name": "XCHG", "count": 48},
    {"name": "BYTE", "count": 2457},
    {"name": "R10D", "count": 537},
    {"name": "R11D", "count": 380},
    {"name": "AL", "count": 1499},
    {"name": "R11", "count": 587},
    {"name": "DIL", "count": 106},
    {"name": "SETNE", "count": 46},
    {"name": "CL", "count": 531},
    {"name": "SETE", "count": 58},
    {"name": "R15", "count": 898},
    {"name": "R12", "count": 770},
    {"name": "R13D", "count": 271},
    {"name": "R13", "count": 555},
    {"name": "CDQ", "count": 25},
    {"name": "IDIV", "count": 8},
    {"name": "R15D", "count": 563},
    {"name": "DEC", "count": 212},
    {"name": "SIL", "count": 113},
    {"name": "MOVSX", "count": 38},
    {"name": "R15B", "count": 81},
    {"name": "DATA16", "count": 52},
    {"name": "MOVSXD", "count": 162},
    {"name": "CMOVG", "count": 23},
    {"name": "CMOVS", "count": 17},
    {"name": "XMM1", "count": 492},
    {"name": "R10", "count": 692},
    {"name": "R15W", "count": 12},
    {"name": "SETB", "count": 19},
    {"name": "R14B", "count": 62},
    {"name": "R8B", "count": 148},
    {"name": "R9B", "count": 170},
    {"name": "R13B", "count": 51},
    {"name": "NEG", "count": 152},
    {"name": "CMOVNS", "count": 17},
    {"name": "MUL", "count": 153},
    {"name": "XMM3", "count": 207},
    {"name": "MOVQ", "count": 51},
    {"name": "CVTSS2SD", "count": 5},
    {"name": "MOVD", "count": 61},
    {"name": "IMUL", "count": 66},
    {"name": "CMOVL", "count": 10},
    {"name": "R12D", "count": 358},
    {"name": "XMM6", "count": 166},
    {"name": "SHR", "count": 145},
    {"name": "SBB", "count": 103},
    {"name": "SETG", "count": 5},
    {"name": "R11B", "count": 60},
    {"name": "SHL", "count": 48},
    {"name": "XMM2", "count": 309},
    {"name": "MOVAPS", "count": 30},
    {"name": "CDQE", "count": 27},
    {"name": "CMOVLE", "count": 7},
    {"name": "CWDE", "count": 4},
    {"name": "R10B", "count": 44},
    {"name": "COMISS", "count": 1},
    {"name": "UCOMISS", "count": 5},
    {"name": "BAD", "count": 205},
    {"name": "BH", "count": 6},
    {"name": "CH", "count": 2},
    {"name": "COMISD", "count": 3},
    {"name": "UCOMISD", "count": 4},
    {"name": "AH", "count": 2},
    {"name": "DH", "count": 3},
    {"name": "R9W", "count": 61},
    {"name": "DX", "count": 248},
    {"name": "DIV", "count": 28},
    {"name": "ESP", "count": 3},
    {"name": "LOCK", "count": 1},
    {"name": "FWAIT", "count": 5},
    {"name": "SAHF", "count": 3},
    {"name": "LAHF", "count": 11},
    {"name": "STI", "count": 4},
    {"name": "REX", "count": 3},
    {"name": "R10W", "count": 39},
    {"name": "CX", "count": 315},
    {"name": "SI", "count": 42},
    {"name": "R12B", "count": 58},
    {"name": "ADC", "count": 9},
    {"name": "SHRD", "count": 10},
    {"name": "NOT", "count": 34},
    {"name": "SETA", "count": 16},
    {"name": "BSF", "count": 10},
    {"name": "OUT", "count": 2},
    {"name": "MOVDQA", "count": 11},
    {"name": "LZCNT", "count": 1},
    {"name": "BSR", "count": 9},
    {"name": "INT1", "count": 3},
    {"name": "IRET", "count": 1},
    {"name": "HLT", "count": 3},
    {"name": "SETP", "count": 3},
    {"name": "CMC", "count": 1},
    {"name": "CLC", "count": 3},
    {"name": "RETF", "count": 1},
    {"name": "CLI", "count": 1},
    {"name": "BX", "count": 380},
    {"name": "BT", "count": 13},
    {"name": "CMOVAE", "count": 31},
    {"name": "BPL", "count": 55},
    {"name": "SETAE", "count": 6},
    {"name": "SETGE", "count": 2},
    {"name": "XADD", "count": 18},
    {"name": "BTS", "count": 2},
    {"name": "VMOVD", "count": 31},
    {"name": "VPXOR", "count": 7},
    {"name": "VPSHUFB", "count": 1},
    {"name": "YMM2", "count": 10},
    {"name": "YMM1", "count": 28},
    {"name": "YMMWORD", "count": 104},
    {"name": "VPMOVMSKB", "count": 4},
    {"name": "VZEROUPPER", "count": 10},
    {"name": "PUNPCKLBW", "count": 1},
    {"name": "PUNPCKLWD", "count": 2},
    {"name": "PCMPEQB", "count": 3},
    {"name": "PMOVMSKB", "count": 15},
    {"name": "TZCNT", "count": 2},
    {"name": "VPUNPCKLWD", "count": 1},
    {"name": "PCMPEQW", "count": 8},
    {"name": "CMPXCHG", "count": 2},
    {"name": "CPUID", "count": 4},
    {"name": "XGETBV", "count": 2},
    {"name": "MOVS", "count": 1},
    {"name": "YMM0", "count": 3},
    {"name": "YMM5", "count": 1},
    {"name": "YMM3", "count": 4},
    {"name": "YMM4", "count": 4},
    {"name": "SFENCE", "count": 2},
    {"name": "XMM5", "count": 120},
    {"name": "XMM4", "count": 131},
    {"name": "MOVUPS", "count": 1},
    {"name": "STOS", "count": 5},
    {"name": "PUNPCKLQDQ", "count": 1},
    {"name": "POR", "count": 3},
    {"name": "BP", "count": 40},
    {"name": "DI", "count": 11},
    {"name": "BSWAP", "count": 2},
    {"name": "ROR", "count": 26},
    {"name": "R11W", "count": 17},
    {"name": "R13W", "count": 11},
    {"name": "R12W", "count": 15},
    {"name": "R14W", "count": 19},
    {"name": "CMOVA", "count": 19},
    {"name": "SETBE", "count": 4},
    {"name": "CMOVBE", "count": 3},
    {"name": "CVTDQ2PD", "count": 7},
    {"name": "XMM7", "count": 93},
    {"name": "MOVSD", "count": 37},
    {"name": "SUBSD", "count": 23},
    {"name": "ADDSD", "count": 47},
    {"name": "MULSD", "count": 77},
    {"name": "CVTPD2DQ", "count": 2},
    {"name": "VMOVQ", "count": 19},
    {"name": "VCVTDQ2PD", "count": 7},
    {"name": "VSUBSD", "count": 14},
    {"name": "VMOVAPD", "count": 20},
    {"name": "VADDSD", "count": 26},
    {"name": "VMULSD", "count": 23},
    {"name": "VFMADD213SD", "count": 2},
    {"name": "VFMSUB213SD", "count": 2},
    {"name": "VCVTPD2DQ", "count": 2},
    {"name": "VXORPD", "count": 1},
    {"name": "PUNPCKLDQ", "count": 1},
    {"name": "PXOR", "count": 3},
    {"name": "CVTPS2PD", "count": 4},
    {"name": "MOVAPD", "count": 20},
    {"name": "PADDQ", "count": 1},
    {"name": "CVTSD2SS", "count": 2},
    {"name": "ORPS", "count": 3},
    {"name": "CVTSS2SI", "count": 3},
    {"name": "CVTSI2SS", "count": 3},
    {"name": "RCR", "count": 6},
    {"name": "DIVSD", "count": 2},
    {"name": "MULPD", "count": 2},
    {"name": "UNPCKLPD", "count": 1},
    {"name": "VPUNPCKLDQ", "count": 1},
    {"name": "VCVTPS2PD", "count": 1},
    {"name": "VPADDQ", "count": 2},
    {"name": "VCVTSD2SS", "count": 1},
    {"name": "VORPS", "count": 3},
    {"name": "VCVTSS2SI", "count": 3},
    {"name": "VCVTSI2SS", "count": 3},
    {"name": "VUCOMISS", "count": 3},
    {"name": "VMOVSD", "count": 1},
    {"name": "VDIVSD", "count": 2},
    {"name": "VUNPCKLPD", "count": 1},
    {"name": "VMULPD", "count": 1},
    {"name": "VMOVDQA", "count": 2},
    {"name": "VADDSS", "count": 1},
    {"name": "CQO", "count": 3},
    {"name": "CVTTSD2SI", "count": 1},
    {"name": "CVTSD2SI", "count": 1},
    {"name": "CVTSI2SD", "count": 1},
    {"name": "XORPD", "count": 1},
    {"name": "VCOMISD", "count": 1},
    {"name": "VFMADD231SD", "count": 2},
    {"name": "CMOVGE", "count": 1}
  ],
  "opcodes": [
    {"name": "PUSH", "count": 1342},
    {"name": "MOV", "count": 7800},
    {"name": "CMP", "count": 1672},
    {"name": "ADD", "count": 703},
    {"name": "XOR", "count": 2110},
    {"name": "POP", "count": 1631},
    {"name": "RET", "count": 1198},
    {"name": "TEST", "count": 2623},
    {"name": "SUB", "count": 875},
    {"name": "NOP", "count": 404},
    {"name": "CALL", "count": 42},
    {"name": "JMP", "count": 28},
    {"name": "AND", "count": 263},
    {"name": "OR", "count": 155},
    {"name": "LEA", "count": 2},
    {"name": "LEAVE", "count": 1}
  ]
}
