{
  "filename": "SysinternalsSuite/sdelete64.asm",
  "behavior": {
    "uses_network": 0,
    "uses_fileops": 0,
    "uses_registry": 0,
    "uses_memory": 0,
    "uses_injection": 0,
    "uses_crypto": 0,
    "uses_persist": 0
  },
  "cfg": {
    "num_blocks": 8732,
    "num_edges": 6640,
    "branch_density": 0.0010,
    "cyclomatic_complexity": 1.0000
  },
  "apis": [
    {"name": "RBP", "count": 771},
    {"name": "RSI", "count": 805},
    {"name": "RDI", "count": 1146},
    {"name": "R12", "count": 280},
    {"name": "R14", "count": 542},
    {"name": "R15", "count": 353},
    {"name": "RSP", "count": 1441},
    {"name": "RAX", "count": 2621},
    {"name": "QWORD", "count": 4660},
    {"name": "R15D", "count": 187},
    {"name": "R13", "count": 168},
    {"name": "RCX", "count": 2700},
    {"name": "R8", "count": 946},
    {"name": "RDX", "count": 1404},
    {"name": "EBP", "count": 182},
    {"name": "ECX", "count": 1550},
    {"name": "EAX", "count": 2859},
    {"name": "EDX", "count": 1214},
    {"name": "DWORD", "count": 2405},
    {"name": "EBX", "count": 542},
    {"name": "ESI", "count": 324},
    {"name": "DATA16", "count": 19},
    {"name": "RIP", "count": 425},
    {"name": "INC", "count": 224},
    {"name": "RBX", "count": 1340},
    {"name": "R8D", "count": 814},
    {"name": "R9", "count": 557},
    {"name": "R15B", "count": 16},
    {"name": "SETE", "count": 31},
    {"name": "INT3", "count": 1395},
    {"name": "R11", "count": 244},
    {"name": "R9D", "count": 518},
    {"name": "EDI", "count": 459},
    {"name": "R8W", "count": 33},
    {"name": "MOVZX", "count": 134},
    {"name": "AX", "count": 268},
    {"name": "XCHG", "count": 11},
    {"name": "BYTE", "count": 914},
    {"name": "R10D", "count": 180},
    {"name": "R11D", "count": 107},
    {"name": "AL", "count": 754},
    {"name": "WORD", "count": 466},
    {"name": "DIL", "count": 38},
    {"name": "SETNE", "count": 26},
    {"name": "CL", "count": 196},
    {"name": "XMM0", "count": 225},
    {"name": "XORPS", "count": 24},
    {"name": "XMMWORD", "count": 295},
    {"name": "R14D", "count": 206},
    {"name": "R13D", "count": 65},
    {"name": "CDQ", "count": 3},
    {"name": "IDIV", "count": 5},
    {"name": "CMOVNE", "count": 34},
    {"name": "DEC", "count": 55},
    {"name": "SIL", "count": 74},
    {"name": "CMOVE", "count": 53},
    {"name": "MOVSX", "count": 14},
    {"name": "BL", "count": 51},
    {"name": "MOVSXD", "count": 74},
    {"name": "CMOVG", "count": 5},
    {"name": "CMOVS", "count": 10},
    {"name": "R12D", "count": 138},
    {"name": "R8B", "count": 92},
    {"name": "IMUL", "count": 29},
    {"name": "DIV", "count": 15},
    {"name": "CQO", "count": 4},
    {"name": "SAR", "count": 19},
    {"name": "CX", "count": 91},
    {"name": "CMOVB", "count": 11},
    {"name": "R14B", "count": 26},
    {"name": "XMM6", "count": 34},
    {"name": "XMM7", "count": 3},
    {"name": "NEG", "count": 62},
    {"name": "CMOVA", "count": 13},
    {"name": "XMM1", "count": 143},
    {"name": "CVTSI2SS", "count": 3},
    {"name": "SHR", "count": 38},
    {"name": "ADDSS", "count": 1},
    {"name": "DIVSS", "count": 1},
    {"name": "MULSS", "count": 2},
    {"name": "CVTPS2PD", "count": 1},
    {"name": "R12B", "count": 22},
    {"name": "DX", "count": 45},
    {"name": "BX", "count": 187},
    {"name": "R10", "count": 243},
    {"name": "R10W", "count": 11},
    {"name": "CMPXCHG", "count": 1},
    {"name": "DL", "count": 80},
    {"name": "SBB", "count": 40},
    {"name": "NOT", "count": 17},
    {"name": "CPUID", "count": 4},
    {"name": "BT", "count": 10},
    {"name": "XGETBV", "count": 2},
    {"name": "R11B", "count": 23},
    {"name": "STOS", "count": 5},
    {"name": "MOVQ", "count": 6},
    {"name": "PUNPCKLQDQ", "count": 1},
    {"name": "YMM0", "count": 3},
    {"name": "YMMWORD", "count": 102},
    {"name": "VZEROUPPER", "count": 6},
    {"name": "SFENCE", "count": 2},
    {"name": "MOVS", "count": 1},
    {"name": "XMM2", "count": 76},
    {"name": "YMM5", "count": 1},
    {"name": "YMM1", "count": 24},
    {"name": "YMM2", "count": 4},
    {"name": "YMM3", "count": 4},
    {"name": "YMM4", "count": 4},
    {"name": "XMM5", "count": 41},
    {"name": "XMM3", "count": 39},
    {"name": "XMM4", "count": 43},
    {"name": "MOVUPS", "count": 1},
    {"name": "MOVAPS", "count": 4},
    {"name": "R9W", "count": 41},
    {"name": "MOVD", "count": 9},
    {"name": "BSWAP", "count": 2},
    {"name": "CMOVL", "count": 1},
    {"name": "R9B", "count": 45},
    {"name": "SETB", "count": 8},
    {"name": "SETA", "count": 6},
    {"name": "R11W", "count": 6},
    {"name": "R13W", "count": 2},
    {"name": "R12W", "count": 11},
    {"name": "BP", "count": 16},
    {"name": "BPL", "count": 21},
    {"name": "MUL", "count": 7},
    {"name": "R10B", "count": 6},
    {"name": "R13B", "count": 7},
    {"name": "R14W", "count": 5},
    {"name": "R15W", "count": 3},
    {"name": "SI", "count": 15},
    {"name": "CMOVAE", "count": 12},
    {"name": "ROR", "count": 24},
    {"name": "CDQE", "count": 4},
    {"name": "XADD", "count": 7},
    {"name": "CMOVBE", "count": 1},
    {"name": "VPXOR", "count": 3},
    {"name": "VPMOVMSKB", "count": 2},
    {"name": "MOVDQA", "count": 4},
    {"name": "PMOVMSKB", "count": 9},
    {"name": "CMOVNS", "count": 1},
    {"name": "SETG", "count": 1},
    {"name": "SETAE", "count": 1},
    {"name": "SHL", "count": 17},
    {"name": "SETBE", "count": 3},
    {"name": "DI", "count": 2},
    {"name": "SETGE", "count": 1},
    {"name": "BSR", "count": 4},
    {"name": "CVTTSD2SI", "count": 1},
    {"name": "MOVAPD", "count": 13},
    {"name": "CVTDQ2PD", "count": 2},
    {"name": "XORPD", "count": 1},
    {"name": "COMISD", "count": 1},
    {"name": "SUBSD", "count": 4},
    {"name": "MULSD", "count": 22},
    {"name": "ADDSD", "count": 12},
    {"name": "DIVSD", "count": 1},
    {"name": "MOVSD", "count": 2},
    {"name": "VMOVQ", "count": 2},
    {"name": "VCVTDQ2PD", "count": 2},
    {"name": "VCOMISD", "count": 1},
    {"name": "VPADDQ", "count": 1},
    {"name": "VSUBSD", "count": 3},
    {"name": "VMULSD", "count": 9},
    {"name": "VFMADD231SD", "count": 2},
    {"name": "VFMSUB213SD", "count": 1},
    {"name": "VADDSD", "count": 9},
    {"name": "VDIVSD", "count": 1},
    {"name": "VMOVAPD", "count": 1},
    {"name": "CVTSD2SI", "count": 1},
    {"name": "CVTSI2SD", "count": 1},
    {"name": "BSF", "count": 2},
    {"name": "PCMPEQW", "count": 2},
    {"name": "POR", "count": 1}
  ],
  "opcodes": [
    {"name": "PUSH", "count": 577},
    {"name": "XOR", "count": 1054},
    {"name": "MOV", "count": 3158},
    {"name": "TEST", "count": 1224},
    {"name": "CMP", "count": 604},
    {"name": "POP", "count": 704},
    {"name": "RET", "count": 586},
    {"name": "ADD", "count": 276},
    {"name": "SUB", "count": 243},
    {"name": "CALL", "count": 12},
    {"name": "NOP", "count": 134},
    {"name": "OR", "count": 72},
    {"name": "AND", "count": 79},
    {"name": "JMP", "count": 9}
  ]
}
